squirreldb/__init__.py
squirreldb/cache.py
squirreldb/client.py
squirreldb/storage.py
squirreldb/types.py
squirreldb_sdk-0.1.0.dist-info/METADATA
squirreldb_sdk-0.1.0.dist-info/WHEEL
squirreldb_sdk-0.1.0.dist-info/licenses/LICENSE
squirreldb_sdk-0.1.0.dist-info/RECORD
