Metadata-Version: 2.4
Name: squirreldb-sdk
Version: 0.1.0
Summary: Client SDK for SquirrelDB realtime database
License: MIT
License-File: LICENSE
Keywords: database,realtime,squirreldb,tcp,websocket
Requires-Python: >=3.9
Requires-Dist: msgpack>=1.0.0
Requires-Dist: websockets>=12.0
Provides-Extra: dev
Requires-Dist: pytest; extra == 'dev'
Requires-Dist: pytest-asyncio; extra == 'dev'
